CheckerService/__init__.py
CheckerService/__main__.py
CheckerService/api.py
CheckerService/const.py
CheckerService/service.py
pih_chk-1.71.dist-info/METADATA
pih_chk-1.71.dist-info/WHEEL
pih_chk-1.71.dist-info/entry_points.txt
pih_chk-1.71.dist-info/top_level.txt
pih_chk-1.71.dist-info/RECORD
