Metadata-Version: 2.1
Name: pih-chk
Version: 1.71
Summary: PIH Checker service package
Home-page: https://pacifichosp.com/
Author: Nikita Karachentsev
Author-email: it@pacifichosp.com
License: MIT
Requires-Dist: ipih
